jukebox_fm/__init__.py
jukebox_fm/jukebox.py
jukebox_fm-0.5.0.dist-info/licenses/LICENSE
jukebox_fm-0.5.0.dist-info/METADATA
jukebox_fm-0.5.0.dist-info/WHEEL
jukebox_fm-0.5.0.dist-info/entry_points.txt
jukebox_fm-0.5.0.dist-info/top_level.txt
jukebox_fm-0.5.0.dist-info/RECORD
