Metadata-Version: 2.4
Name: jukebox-fm
Version: 0.5.0
Summary: Play LastFM music recommendations using: mpd, yt-dlp and python
Author-email: Nathan Paul <mail@polarhive.net>
License: GNU GENERAL PUBLIC LICENSE
Project-URL: Homepage, https://github.com/polarhive/jukebox
Project-URL: Issues, https://github.com/polarhive/jukebox/issues
Keywords: mpd,lastfm,music,yt-dlp
Classifier: License :: OSI Approved :: GNU General Public License v3 (GPLv3)
Classifier: Programming Language :: Python :: 3
Classifier: Topic :: Multimedia :: Sound/Audio :: Players
Classifier: Operating System :: OS Independent
Requires-Python: >=3.11
License-File: LICENSE
Requires-Dist: requests>=2.32.5
Requires-Dist: yt-dlp
Requires-Dist: toml
Requires-Dist: python-mpd2
Dynamic: license-file
